odoo/addons/fleet_vehicle_service_calendar/README.rst
odoo/addons/fleet_vehicle_service_calendar/__init__.py
odoo/addons/fleet_vehicle_service_calendar/__manifest__.py
odoo/addons/fleet_vehicle_service_calendar/i18n/fleet_vehicle_service_calendar.pot
odoo/addons/fleet_vehicle_service_calendar/i18n/fr.po
odoo/addons/fleet_vehicle_service_calendar/i18n/it.po
odoo/addons/fleet_vehicle_service_calendar/models/__init__.py
odoo/addons/fleet_vehicle_service_calendar/models/calendar_event.py
odoo/addons/fleet_vehicle_service_calendar/models/fleet_vehicle_log_services.py
odoo/addons/fleet_vehicle_service_calendar/readme/CONTRIBUTORS.rst
odoo/addons/fleet_vehicle_service_calendar/readme/DESCRIPTION.rst
odoo/addons/fleet_vehicle_service_calendar/static/description/icon.png
odoo/addons/fleet_vehicle_service_calendar/static/description/index.html
odoo/addons/fleet_vehicle_service_calendar/tests/__init__.py
odoo/addons/fleet_vehicle_service_calendar/tests/test_vehicle_service_calendar.py
odoo/addons/fleet_vehicle_service_calendar/views/calendar_event_views.xml
odoo/addons/fleet_vehicle_service_calendar/views/fleet_vehicle_log_services_views.xml
odoo13_addon_fleet_vehicle_service_calendar-13.0.1.0.1.dist-info/METADATA
odoo13_addon_fleet_vehicle_service_calendar-13.0.1.0.1.dist-info/WHEEL
odoo13_addon_fleet_vehicle_service_calendar-13.0.1.0.1.dist-info/top_level.txt
odoo13_addon_fleet_vehicle_service_calendar-13.0.1.0.1.dist-info/RECORD
